hcaptcha/__init__.py
hcaptcha/hcaptcha.py
hcaptcha-0.2.0.dist-info/WHEEL
hcaptcha-0.2.0.dist-info/METADATA
hcaptcha-0.2.0.dist-info/RECORD
