Metadata-Version: 2.1
Name: hcaptcha
Version: 0.2.0
Summary: A Python package for integrating hCaptcha, a popular captcha service, into various applications for enhanced security and user verification.
Home-page: https://github.com/VaibhavSys/hcaptcha
License: MIT
Keywords: captcha,hcaptcha,async,aiohttp,aiodns,asyncio,async,user verification,security,enhanced security,captcha service,captcha integration
Author: Vaibhav Dhiman
Author-email: vaibhavsys@protonmail.com
Requires-Python: >=3.5,<4.0
Classifier: Intended Audience :: Developers
Classifier: License :: OSI Approved :: MIT License
Classifier: Operating System :: OS Independent
Classifier: Programming Language :: Python :: 3
Classifier: Programming Language :: Python :: 3.10
Classifier: Programming Language :: Python :: 3.5
Classifier: Programming Language :: Python :: 3.6
Classifier: Programming Language :: Python :: 3.7
Classifier: Programming Language :: Python :: 3.8
Classifier: Programming Language :: Python :: 3.9
Requires-Dist: aiodns (>=3.0.0,<4.0.0)
Requires-Dist: aiohttp (>=3.8.4,<4.0.0)
Project-URL: Repository, https://github.com/VaibhavSys/hcaptcha
